tidytuesdaypy/__init__.py
tidytuesdaypy/__main__.py
tidytuesdaypy-0.1.0.dist-info/LICENSE
tidytuesdaypy-0.1.0.dist-info/WHEEL
tidytuesdaypy-0.1.0.dist-info/METADATA
tidytuesdaypy-0.1.0.dist-info/RECORD
