Metadata-Version: 2.1
Name: tidytuesdaypy
Version: 0.1.0
Summary: Extract weekly TidyTuesday Data/Readme
Home-page: https://github.com/alwinw/tidytuesdaypy
License: MIT
Author: alwinw
Author-email: 16846521+alwinw@users.noreply.github.com
Requires-Python: >=3.7,<4.0
Classifier: License :: OSI Approved :: MIT License
Classifier: Programming Language :: Python :: 3
Classifier: Programming Language :: Python :: 3.10
Classifier: Programming Language :: Python :: 3.7
Classifier: Programming Language :: Python :: 3.8
Classifier: Programming Language :: Python :: 3.9
Project-URL: Documentation, https://github.com/alwinw/tidytuesdaypy
Project-URL: Repository, https://github.com/alwinw/tidytuesdaypy
